Metadata-Version: 2.1
Name: pyregedit
Version: 1.0.0
Summary: registry edit (注册表操作)
Home-page: https://github.com/HaddyYang/pyregedit
Author: Haddy Yang (杨仕航)
License: MIT License
Keywords: registry edit
Platform: win32
Platform: win_amd64
Classifier: Development Status :: 4 - Beta
Classifier: License :: OSI Approved :: MIT License
